{
    "request": {
        "method": "GET",
        "path": "/api/v1/process/21/run?page=5"
    },
    "response": {
        "body": [
            {
                "process_id": 21,
                "id": 210041,
                "name": "Sunt enim vero fugiat alias.",
                "metadata": {
                    "cpr": 1,
                    "name": "Prof. Gerhard Wiegand",
                    "branch": "Feest-Parisian"
                },
                "steps": [
                    {
                        "status": "SUCCESS",
                        "started_at": "2025-09-20T23:08:34+02:00",
                        "finished_at": "2025-09-20T23:08:53+02:00",
                        "failure": null
                    },
                    {
                        "status": "SUCCESS",
                        "started_at": "2025-09-20T23:11:18+02:00",
                        "finished_at": "2025-09-20T23:11:28+02:00",
                        "failure": null
                    },
                    {
                        "status": "SUCCESS",
                        "started_at": "2025-09-20T23:21:41+02:00",
                        "finished_at": "2025-09-20T23:22:18+02:00",
                        "failure": null
                    },
                    {
                        "status": "FAILED",
                        "started_at": "2025-09-20T23:24:07+02:00",
                        "finished_at": "2025-09-20T23:24:47+02:00",
                        "failure": {
                            "code": "Fejlkode",
                            "message": "Fejlbesked",
                            "retryable": false,
                            "occurred_at": "2025-09-20T23:24:47+02:00"
                        }
                    },
                    {
                        "status": "PENDING",
                        "started_at": "2025-09-20T23:25:34+02:00",
                        "finished_at": "2025-09-20T23:26:04+02:00",
                        "failure": null
                    },
                    {
                        "status": "PENDING",
                        "started_at": "2025-09-20T23:35:44+02:00",
                        "finished_at": "2025-09-20T23:35:57+02:00",
                        "failure": null
                    }
                ]
            },
            {
                "process_id": 21,
                "id": 210042,
                "name": "Et enim ut molestias qui recusandae.",
                "metadata": {
                    "cpr": 67282,
                    "name": "Mr. Soledad Waters",
                    "branch": "Gusikowski and Sons"
                },
                "steps": [
                    {
                        "status": "SUCCESS",
                        "started_at": "2025-09-20T23:01:12+02:00",
                        "finished_at": "2025-09-20T23:01:44+02:00",
                        "failure": null
                    },
                    {
                        "status": "SUCCESS",
                        "started_at": "2025-09-20T23:17:28+02:00",
                        "finished_at": "2025-09-20T23:18:00+02:00",
                        "failure": null
                    },
                    {
                        "status": "SUCCESS",
                        "started_at": "2025-09-20T23:24:24+02:00",
                        "finished_at": "2025-09-20T23:24:44+02:00",
                        "failure": null
                    },
                    {
                        "status": "SUCCESS",
                        "started_at": "2025-09-20T23:37:05+02:00",
                        "finished_at": "2025-09-20T23:37:27+02:00",
                        "failure": null
                    },
                    {
                        "status": "SUCCESS",
                        "started_at": "2025-09-20T23:51:32+02:00",
                        "finished_at": "2025-09-20T23:52:12+02:00",
                        "failure": null
                    },
                    {
                        "status": "FAILED",
                        "started_at": "2025-09-21T00:02:23+02:00",
                        "finished_at": "2025-09-21T00:02:41+02:00",
                        "failure": {
                            "code": "Fejlkode",
                            "message": "Fejlbesked",
                            "retryable": true,
                            "occurred_at": "2025-09-21T00:02:39+02:00"
                        }
                    }
                ]
            },
            {
                "process_id": 21,
                "id": 210043,
                "name": "Quis iure ab iusto voluptatem.",
                "metadata": {
                    "cpr": 324,
                    "name": "Prof. Bartholome Herzog DVM",
                    "branch": "Wiza-Nikolaus"
                },
                "steps": [
                    {
                        "status": "SUCCESS",
                        "started_at": "2025-09-20T23:09:20+02:00",
                        "finished_at": "2025-09-20T23:09:33+02:00",
                        "failure": null
                    },
                    {
                        "status": "SUCCESS",
                        "started_at": "2025-09-20T23:23:13+02:00",
                        "finished_at": "2025-09-20T23:23:19+02:00",
                        "failure": null
                    },
                    {
                        "status": "SUCCESS",
                        "started_at": "2025-09-20T23:25:00+02:00",
                        "finished_at": "2025-09-20T23:25:04+02:00",
                        "failure": null
                    },
                    {
                        "status": "SUCCESS",
                        "started_at": "2025-09-20T23:27:02+02:00",
                        "finished_at": "2025-09-20T23:27:35+02:00",
                        "failure": null
                    },
                    {
                        "status": "FAILED",
                        "started_at": "2025-09-20T23:37:41+02:00",
                        "finished_at": "2025-09-20T23:38:12+02:00",
                        "failure": {
                            "code": "Fejlkode",
                            "message": "Fejlbesked",
                            "retryable": true,
                            "occurred_at": "2025-09-20T23:38:09+02:00"
                        }
                    },
                    {
                        "status": "PENDING",
                        "started_at": "2025-09-20T23:43:18+02:00",
                        "finished_at": "2025-09-20T23:43:57+02:00",
                        "failure": null
                    }
                ]
            },
            {
                "process_id": 21,
                "id": 210044,
                "name": "Modi omnis aperiam in.",
                "metadata": {
                    "cpr": 39621140,
                    "name": "Helene Eichmann",
                    "branch": "Rath Ltd"
                },
                "steps": [
                    {
                        "status": "SUCCESS",
                        "started_at": "2025-09-20T23:00:00+02:00",
                        "finished_at": "2025-09-20T23:00:32+02:00",
                        "failure": null
                    },
                    {
                        "status": "SUCCESS",
                        "started_at": "2025-09-20T23:14:21+02:00",
                        "finished_at": "2025-09-20T23:14:36+02:00",
                        "failure": null
                    },
                    {
                        "status": "SUCCESS",
                        "started_at": "2025-09-20T23:28:33+02:00",
                        "finished_at": "2025-09-20T23:29:09+02:00",
                        "failure": null
                    },
                    {
                        "status": "SUCCESS",
                        "started_at": "2025-09-20T23:43:37+02:00",
                        "finished_at": "2025-09-20T23:43:58+02:00",
                        "failure": null
                    },
                    {
                        "status": "SUCCESS",
                        "started_at": "2025-09-20T23:57:16+02:00",
                        "finished_at": "2025-09-20T23:57:21+02:00",
                        "failure": null
                    },
                    {
                        "status": "FAILED",
                        "started_at": "2025-09-21T00:04:58+02:00",
                        "finished_at": "2025-09-21T00:05:29+02:00",
                        "failure": {
                            "code": "Fejlkode",
                            "message": "Fejlbesked",
                            "retryable": false,
                            "occurred_at": "2025-09-21T00:05:29+02:00"
                        }
                    }
                ]
            },
            {
                "process_id": 21,
                "id": 210045,
                "name": "Asperiores qui labore sunt ea.",
                "metadata": {
                    "cpr": 8,
                    "name": "Drake Kutch Jr.",
                    "branch": "Dickens, Towne and Murphy"
                },
                "steps": [
                    {
                        "status": "FAILED",
                        "started_at": "2025-09-20T23:10:53+02:00",
                        "finished_at": "2025-09-20T23:11:27+02:00",
                        "failure": {
                            "code": "Fejlkode",
                            "message": "Fejlbesked",
                            "retryable": false,
                            "occurred_at": "2025-09-20T23:11:25+02:00"
                        }
                    },
                    {
                        "status": "PENDING",
                        "started_at": "2025-09-20T23:18:08+02:00",
                        "finished_at": "2025-09-20T23:18:21+02:00",
                        "failure": null
                    },
                    {
                        "status": "PENDING",
                        "started_at": "2025-09-20T23:27:17+02:00",
                        "finished_at": "2025-09-20T23:27:47+02:00",
                        "failure": null
                    },
                    {
                        "status": "PENDING",
                        "started_at": "2025-09-20T23:31:12+02:00",
                        "finished_at": "2025-09-20T23:31:38+02:00",
                        "failure": null
                    },
                    {
                        "status": "PENDING",
                        "started_at": "2025-09-20T23:41:59+02:00",
                        "finished_at": "2025-09-20T23:42:07+02:00",
                        "failure": null
                    },
                    {
                        "status": "PENDING",
                        "started_at": "2025-09-20T23:58:12+02:00",
                        "finished_at": "2025-09-20T23:58:44+02:00",
                        "failure": null
                    }
                ]
            },
            {
                "process_id": 21,
                "id": 210046,
                "name": "Harum optio dolores quisquam.",
                "metadata": {
                    "cpr": 6629,
                    "name": "Corine Johns",
                    "branch": "Orn, Mosciski and Emmerich"
                },
                "steps": [
                    {
                        "status": "SUCCESS",
                        "started_at": "2025-09-20T23:01:40+02:00",
                        "finished_at": "2025-09-20T23:02:13+02:00",
                        "failure": null
                    },
                    {
                        "status": "SUCCESS",
                        "started_at": "2025-09-20T23:09:15+02:00",
                        "finished_at": "2025-09-20T23:09:43+02:00",
                        "failure": null
                    },
                    {
                        "status": "SUCCESS",
                        "started_at": "2025-09-20T23:25:34+02:00",
                        "finished_at": "2025-09-20T23:25:50+02:00",
                        "failure": null
                    },
                    {
                        "status": "SUCCESS",
                        "started_at": "2025-09-20T23:28:21+02:00",
                        "finished_at": "2025-09-20T23:28:52+02:00",
                        "failure": null
                    },
                    {
                        "status": "FAILED",
                        "started_at": "2025-09-20T23:30:18+02:00",
                        "finished_at": "2025-09-20T23:30:36+02:00",
                        "failure": {
                            "code": "Fejlkode",
                            "message": "Fejlbesked",
                            "retryable": true,
                            "occurred_at": "2025-09-20T23:30:34+02:00"
                        }
                    },
                    {
                        "status": "PENDING",
                        "started_at": "2025-09-20T23:41:49+02:00",
                        "finished_at": "2025-09-20T23:42:02+02:00",
                        "failure": null
                    }
                ]
            },
            {
                "process_id": 21,
                "id": 210047,
                "name": "Omnis sit vel.",
                "metadata": {
                    "cpr": 84,
                    "name": "Dr. Roel Wiza III",
                    "branch": "Dibbert-Mayer"
                },
                "steps": [
                    {
                        "status": "FAILED",
                        "started_at": "2025-09-20T23:13:23+02:00",
                        "finished_at": "2025-09-20T23:13:43+02:00",
                        "failure": {
                            "code": "Fejlkode",
                            "message": "Fejlbesked",
                            "retryable": true,
                            "occurred_at": "2025-09-20T23:13:41+02:00"
                        }
                    },
                    {
                        "status": "PENDING",
                        "started_at": "2025-09-20T23:25:05+02:00",
                        "finished_at": "2025-09-20T23:25:08+02:00",
                        "failure": null
                    },
                    {
                        "status": "PENDING",
                        "started_at": "2025-09-20T23:37:11+02:00",
                        "finished_at": "2025-09-20T23:37:37+02:00",
                        "failure": null
                    },
                    {
                        "status": "PENDING",
                        "started_at": "2025-09-20T23:41:07+02:00",
                        "finished_at": "2025-09-20T23:41:45+02:00",
                        "failure": null
                    },
                    {
                        "status": "PENDING",
                        "started_at": "2025-09-20T23:57:00+02:00",
                        "finished_at": "2025-09-20T23:57:32+02:00",
                        "failure": null
                    },
                    {
                        "status": "PENDING",
                        "started_at": "2025-09-21T00:11:20+02:00",
                        "finished_at": "2025-09-21T00:11:41+02:00",
                        "failure": null
                    }
                ]
            },
            {
                "process_id": 21,
                "id": 210048,
                "name": "Quia in et.",
                "metadata": {
                    "cpr": 28,
                    "name": "Albin Spinka",
                    "branch": "Quigley-Runolfsson"
                },
                "steps": [
                    {
                        "status": "SUCCESS",
                        "started_at": "2025-09-20T23:09:40+02:00",
                        "finished_at": "2025-09-20T23:10:12+02:00",
                        "failure": null
                    },
                    {
                        "status": "FAILED",
                        "started_at": "2025-09-20T23:25:50+02:00",
                        "finished_at": "2025-09-20T23:26:32+02:00",
                        "failure": {
                            "code": "Fejlkode",
                            "message": "Fejlbesked",
                            "retryable": false,
                            "occurred_at": "2025-09-20T23:26:31+02:00"
                        }
                    },
                    {
                        "status": "PENDING",
                        "started_at": "2025-09-20T23:40:47+02:00",
                        "finished_at": "2025-09-20T23:40:53+02:00",
                        "failure": null
                    },
                    {
                        "status": "PENDING",
                        "started_at": "2025-09-20T23:53:56+02:00",
                        "finished_at": "2025-09-20T23:54:31+02:00",
                        "failure": null
                    },
                    {
                        "status": "PENDING",
                        "started_at": "2025-09-21T00:05:30+02:00",
                        "finished_at": "2025-09-21T00:06:06+02:00",
                        "failure": null
                    },
                    {
                        "status": "PENDING",
                        "started_at": "2025-09-21T00:09:42+02:00",
                        "finished_at": "2025-09-21T00:10:22+02:00",
                        "failure": null
                    }
                ]
            },
            {
                "process_id": 21,
                "id": 210049,
                "name": "Neque veniam ut quia quisquam harum.",
                "metadata": {
                    "cpr": 386,
                    "name": "Dr. Kameron Bruen",
                    "branch": "Green Ltd"
                },
                "steps": [
                    {
                        "status": "SUCCESS",
                        "started_at": "2025-09-20T23:07:54+02:00",
                        "finished_at": "2025-09-20T23:08:04+02:00",
                        "failure": null
                    },
                    {
                        "status": "SUCCESS",
                        "started_at": "2025-09-20T23:18:23+02:00",
                        "finished_at": "2025-09-20T23:18:32+02:00",
                        "failure": null
                    },
                    {
                        "status": "SUCCESS",
                        "started_at": "2025-09-20T23:34:26+02:00",
                        "finished_at": "2025-09-20T23:35:01+02:00",
                        "failure": null
                    },
                    {
                        "status": "FAILED",
                        "started_at": "2025-09-20T23:47:04+02:00",
                        "finished_at": "2025-09-20T23:47:12+02:00",
                        "failure": {
                            "code": "Fejlkode",
                            "message": "Fejlbesked",
                            "retryable": false,
                            "occurred_at": "2025-09-20T23:47:12+02:00"
                        }
                    },
                    {
                        "status": "PENDING",
                        "started_at": "2025-09-20T23:53:00+02:00",
                        "finished_at": "2025-09-20T23:53:42+02:00",
                        "failure": null
                    },
                    {
                        "status": "PENDING",
                        "started_at": "2025-09-20T23:54:36+02:00",
                        "finished_at": "2025-09-20T23:54:41+02:00",
                        "failure": null
                    }
                ]
            },
            {
                "process_id": 21,
                "id": 210050,
                "name": "Rerum velit accusamus quo.",
                "metadata": {
                    "cpr": 94091,
                    "name": "Ettie Aufderhar IV",
                    "branch": "Lowe, Goldner and Runte"
                },
                "steps": [
                    {
                        "status": "SUCCESS",
                        "started_at": "2025-09-20T23:05:06+02:00",
                        "finished_at": "2025-09-20T23:05:28+02:00",
                        "failure": null
                    },
                    {
                        "status": "SUCCESS",
                        "started_at": "2025-09-20T23:05:50+02:00",
                        "finished_at": "2025-09-20T23:06:24+02:00",
                        "failure": null
                    },
                    {
                        "status": "SUCCESS",
                        "started_at": "2025-09-20T23:14:09+02:00",
                        "finished_at": "2025-09-20T23:14:48+02:00",
                        "failure": null
                    },
                    {
                        "status": "SUCCESS",
                        "started_at": "2025-09-20T23:26:24+02:00",
                        "finished_at": "2025-09-20T23:26:49+02:00",
                        "failure": null
                    },
                    {
                        "status": "SUCCESS",
                        "started_at": "2025-09-20T23:28:29+02:00",
                        "finished_at": "2025-09-20T23:28:42+02:00",
                        "failure": null
                    },
                    {
                        "status": "SUCCESS",
                        "started_at": "2025-09-20T23:43:55+02:00",
                        "finished_at": "2025-09-20T23:44:19+02:00",
                        "failure": null
                    }
                ]
            }
        ]
    }
}